[
 [
  {
   "start": 0.03096875,
   "end": 1.81971875
  },
  {
   "A": "SPEAKER_03"
  }
 ],
 [
  {
   "start": 1.95471875,
   "end": 5.19471875
  },
  {
   "B": "SPEAKER_03"
  }
 ],
 [
  {
   "start": 5.498468750000001,
   "end": 20.33159375
  },
  {
   "C": "SPEAKER_03"
  }
 ],
 [
  {
   "start": 19.605968750000002,
   "end": 21.63096875
  },
  {
   "D": "SPEAKER_00"
  }
 ],
 [
  {
   "start": 21.63096875,
   "end": 27.891593750000002
  },
  {
   "E": "SPEAKER_03"
  }
 ],
 [
  {
   "start": 21.64784375,
   "end": 21.83346875
  },
  {
   "F": "SPEAKER_00"
  }
 ],
 [
  {
   "start": 26.10284375,
   "end": 26.44034375
  },
  {
   "G": "SPEAKER_00"
  }
 ],
 [
  {
   "start": 27.469718750000002,
   "end": 28.34721875
  },
  {
   "H": "SPEAKER_00"
  }
 ],
 [
  {
   "start": 28.34721875,
   "end": 29.02221875
  },
  {
   "I": "SPEAKER_03"
  }
 ],
 [
  {
   "start": 29.089718750000003,
   "end": 48.19221875
  },
  {
   "J": "SPEAKER_03"
  }
 ],
 [
  {
   "start": 30.355343750000003,
   "end": 31.35096875
  },
  {
   "K": "SPEAKER_02"
  }
 ],
 [
  {
   "start": 44.91846875,
   "end": 46.268468750000004
  },
  {
   "L": "SPEAKER_00"
  }
 ],
 [
  {
   "start": 48.52971875,
   "end": 77.36909375
  },
  {
   "M": "SPEAKER_03"
  }
 ],
 [
  {
   "start": 73.72409375000001,
   "end": 73.92659375000001
  },
  {
   "N": "SPEAKER_02"
  }
 ],
 [
  {
   "start": 77.18346875,
   "end": 85.53659375000001
  },
  {
   "O": "SPEAKER_02"
  }
 ],
 [
  {
   "start": 85.77284375,
   "end": 95.52659375
  },
  {
   "P": "SPEAKER_02"
  }
 ],
 [
  {
   "start": 93.90659375,
   "end": 94.58159375000001
  },
  {
   "Q": "SPEAKER_00"
  }
 ],
 [
  {
   "start": 95.98221875,
   "end": 99.67784375000001
  },
  {
   "R": "SPEAKER_02"
  }
 ],
 [
  {
   "start": 100.15034375,
   "end": 105.19596875
  },
  {
   "S": "SPEAKER_02"
  }
 ],
 [
  {
   "start": 104.82471875,
   "end": 105.34784375000001
  },
  {
   "T": "SPEAKER_03"
  }
 ],
 [
  {
   "start": 105.41534375,
   "end": 108.62159375
  },
  {
   "U": "SPEAKER_03"
  }
 ],
 [
  {
   "start": 106.93409375,
   "end": 106.96784375
  },
  {
   "V": "SPEAKER_02"
  }
 ],
 [
  {
   "start": 108.62159375,
   "end": 111.10221875
  },
  {
   "W": "SPEAKER_02"
  }
 ],
 [
  {
   "start": 110.78159375000001,
   "end": 123.26909375000001
  },
  {
   "X": "SPEAKER_03"
  }
 ],
 [
  {
   "start": 115.65846875000001,
   "end": 116.13096875000001
  },
  {
   "Y": "SPEAKER_02"
  }
 ],
 [
  {
   "start": 117.78471875000001,
   "end": 118.24034375000001
  },
  {
   "Z": "SPEAKER_02"
  }
 ],
 [
  {
   "start": 122.59409375000001,
   "end": 122.98221875
  },
  {
   "AA": "SPEAKER_04"
  }
 ],
 [
  {
   "start": 123.26909375000001,
   "end": 129.36096875
  },
  {
   "AB": "SPEAKER_04"
  }
 ],
 [
  {
   "start": 129.46221875,
   "end": 129.83346875
  },
  {
   "AC": "SPEAKER_04"
  }
 ],
 [
  {
   "start": 129.90096875,
   "end": 134.98034375
  },
  {
   "AD": "SPEAKER_04"
  }
 ],
 [
  {
   "start": 135.26721875,
   "end": 151.29846875
  },
  {
   "AE": "SPEAKER_04"
  }
 ],
 [
  {
   "start": 150.80909375000002,
   "end": 150.87659375
  },
  {
   "AF": "SPEAKER_03"
  }
 ],
 [
  {
   "start": 151.29846875,
   "end": 151.43346875
  },
  {
   "AG": "SPEAKER_03"
  }
 ],
 [
  {
   "start": 151.43346875,
   "end": 151.46721875
  },
  {
   "AH": "SPEAKER_04"
  }
 ],
 [
  {
   "start": 151.46721875,
   "end": 151.53471875
  },
  {
   "AI": "SPEAKER_03"
  }
 ],
 [
  {
   "start": 151.53471875,
   "end": 153.34034375000002
  },
  {
   "AJ": "SPEAKER_04"
  }
 ],
 [
  {
   "start": 153.34034375000002,
   "end": 153.37409375000001
  },
  {
   "AK": "SPEAKER_03"
  }
 ],
 [
  {
   "start": 153.37409375000001,
   "end": 153.79596875000001
  },
  {
   "AL": "SPEAKER_02"
  }
 ],
 [
  {
   "start": 153.79596875000001,
   "end": 153.84659375
  },
  {
   "AM": "SPEAKER_04"
  }
 ],
 [
  {
   "start": 153.84659375,
   "end": 153.94784375
  },
  {
   "AN": "SPEAKER_02"
  }
 ],
 [
  {
   "start": 153.94784375,
   "end": 156.44534375
  },
  {
   "AO": "SPEAKER_04"
  }
 ],
 [
  {
   "start": 154.04909375,
   "end": 154.09971875000002
  },
  {
   "AP": "SPEAKER_02"
  }
 ],
 [
  {
   "start": 154.09971875000002,
   "end": 154.15034375000002
  },
  {
   "AQ": "SPEAKER_03"
  }
 ],
 [
  {
   "start": 154.15034375000002,
   "end": 154.26846875
  },
  {
   "AR": "SPEAKER_02"
  }
 ],
 [
  {
   "start": 156.58034375,
   "end": 169.67534375000002
  },
  {
   "AS": "SPEAKER_04"
  }
 ],
 [
  {
   "start": 165.97971875000002,
   "end": 166.46909375
  },
  {
   "AT": "SPEAKER_02"
  }
 ],
 [
  {
   "start": 167.54909375,
   "end": 168.17346875
  },
  {
   "AU": "SPEAKER_02"
  }
 ],
 [
  {
   "start": 169.82721875000001,
   "end": 170.26596875
  },
  {
   "AV": "SPEAKER_04"
  }
 ],
 [
  {
   "start": 170.48534375,
   "end": 173.03346875
  },
  {
   "AW": "SPEAKER_04"
  }
 ],
 [
  {
   "start": 170.60346875000002,
   "end": 171.22784375
  },
  {
   "AX": "SPEAKER_02"
  }
 ],
 [
  {
   "start": 173.03346875,
   "end": 173.26971875
  },
  {
   "AY": "SPEAKER_02"
  }
 ],
 [
  {
   "start": 173.26971875,
   "end": 173.91096875000002
  },
  {
   "AZ": "SPEAKER_04"
  }
 ],
 [
  {
   "start": 173.53971875000002,
   "end": 173.55659375000002
  },
  {
   "BA": "SPEAKER_01"
  }
 ],
 [
  {
   "start": 173.55659375000002,
   "end": 181.82534375
  },
  {
   "BB": "SPEAKER_02"
  }
 ],
 [
  {
   "start": 176.71221875,
   "end": 177.11721875
  },
  {
   "BC": "SPEAKER_04"
  }
 ],
 [
  {
   "start": 177.84284375000001,
   "end": 178.68659375000001
  },
  {
   "BD": "SPEAKER_04"
  }
 ],
 [
  {
   "start": 180.72846875000002,
   "end": 181.09971875000002
  },
  {
   "BE": "SPEAKER_04"
  }
 ],
 [
  {
   "start": 181.82534375,
   "end": 181.84221875
  },
  {
   "BF": "SPEAKER_04"
  }
 ],
 [
  {
   "start": 181.84221875,
   "end": 181.87596875
  },
  {
   "BG": "SPEAKER_02"
  }
 ],
 [
  {
   "start": 182.29784375,
   "end": 186.36471875
  },
  {
   "BH": "SPEAKER_04"
  }
 ],
 [
  {
   "start": 186.36471875,
   "end": 186.63471875000002
  },
  {
   "BI": "SPEAKER_01"
  }
 ],
 [
  {
   "start": 186.63471875000002,
   "end": 190.29659375
  },
  {
   "BJ": "SPEAKER_04"
  }
 ],
 [
  {
   "start": 190.66784375,
   "end": 208.80846875
  },
  {
   "BK": "SPEAKER_04"
  }
 ],
 [
  {
   "start": 203.02034375000002,
   "end": 203.03721875000002
  },
  {
   "BL": "SPEAKER_00"
  }
 ],
 [
  {
   "start": 203.03721875000002,
   "end": 203.12159375000002
  },
  {
   "BM": "SPEAKER_01"
  }
 ],
 [
  {
   "start": 209.31471875000003,
   "end": 213.12846875000002
  },
  {
   "BN": "SPEAKER_04"
  }
 ],
 [
  {
   "start": 213.29721875,
   "end": 223.28721875000002
  },
  {
   "BO": "SPEAKER_02"
  }
 ],
 [
  {
   "start": 222.00471875000002,
   "end": 222.25784375
  },
  {
   "BP": "SPEAKER_04"
  }
 ],
 [
  {
   "start": 223.28721875000002,
   "end": 236.01096875000002
  },
  {
   "BQ": "SPEAKER_04"
  }
 ],
 [
  {
   "start": 227.92784375000002,
   "end": 228.16409375
  },
  {
   "BR": "SPEAKER_02"
  }
 ],
 [
  {
   "start": 231.03284375,
   "end": 231.37034375000002
  },
  {
   "BS": "SPEAKER_02"
  }
 ],
 [
  {
   "start": 236.01096875000002,
   "end": 243.92534375000002
  },
  {
   "BT": "SPEAKER_02"
  }
 ],
 [
  {
   "start": 244.04346875000002,
   "end": 249.78096875000003
  },
  {
   "BU": "SPEAKER_00"
  }
 ],
 [
  {
   "start": 249.94971875000002,
   "end": 260.63159375000004
  },
  {
   "BV": "SPEAKER_00"
  }
 ],
 [
  {
   "start": 260.63159375000004,
   "end": 261.22221875
  },
  {
   "BW": "SPEAKER_01"
  }
 ],
 [
  {
   "start": 261.08721875000003,
   "end": 273.72659375
  },
  {
   "BX": "SPEAKER_00"
  }
 ],
 [
  {
   "start": 261.47534375000004,
   "end": 262.79159375
  },
  {
   "BY": "SPEAKER_01"
  }
 ],
 [
  {
   "start": 268.84971875,
   "end": 269.87909375000004
  },
  {
   "BZ": "SPEAKER_02"
  }
 ],
 [
  {
   "start": 272.91659375,
   "end": 274.84034375000005
  },
  {
   "CA": "SPEAKER_02"
  }
 ],
 [
  {
   "start": 274.06409375000004,
   "end": 279.58221875000004
  },
  {
   "CB": "SPEAKER_00"
  }
 ],
 [
  {
   "start": 279.58221875000004,
   "end": 279.66659375
  },
  {
   "CC": "SPEAKER_02"
  }
 ],
 [
  {
   "start": 279.66659375,
   "end": 279.68346875000003
  },
  {
   "CD": "SPEAKER_00"
  }
 ],
 [
  {
   "start": 279.68346875000003,
   "end": 280.03784375000004
  },
  {
   "CE": "SPEAKER_02"
  }
 ],
 [
  {
   "start": 279.90284375000005,
   "end": 281.55659375
  },
  {
   "CF": "SPEAKER_00"
  }
 ],
 [
  {
   "start": 281.53971875,
   "end": 282.87284375
  },
  {
   "CG": "SPEAKER_02"
  }
 ],
 [
  {
   "start": 282.87284375,
   "end": 302.68409375000005
  },
  {
   "CH": "SPEAKER_00"
  }
 ],
 [
  {
   "start": 284.79659375,
   "end": 285.03284375000004
  },
  {
   "CI": "SPEAKER_02"
  }
 ],
 [
  {
   "start": 291.17534375,
   "end": 291.22596875
  },
  {
   "CJ": "SPEAKER_02"
  }
 ],
 [
  {
   "start": 291.46221875000003,
   "end": 291.51284375
  },
  {
   "CK": "SPEAKER_02"
  }
 ],
 [
  {
   "start": 293.04846875000004,
   "end": 293.13284375
  },
  {
   "CL": "SPEAKER_02"
  }
 ],
 [
  {
   "start": 296.20409375,
   "end": 296.32221875000005
  },
  {
   "CM": "SPEAKER_02"
  }
 ],
 [
  {
   "start": 297.33471875000004,
   "end": 297.73971875
  },
  {
   "CN": "SPEAKER_02"
  }
 ],
 [
  {
   "start": 298.65096875,
   "end": 299.07284375
  },
  {
   "CO": "SPEAKER_02"
  }
 ],
 [
  {
   "start": 302.48159375,
   "end": 309.46784375000004
  },
  {
   "CP": "SPEAKER_02"
  }
 ],
 [
  {
   "start": 309.80534375,
   "end": 323.79471875
  },
  {
   "CQ": "SPEAKER_02"
  }
 ],
 [
  {
   "start": 316.74096875000004,
   "end": 317.11221875
  },
  {
   "CR": "SPEAKER_01"
  }
 ],
 [
  {
   "start": 317.11221875,
   "end": 317.17971875
  },
  {
   "CS": "SPEAKER_00"
  }
 ],
 [
  {
   "start": 317.17971875,
   "end": 317.21346875
  },
  {
   "CT": "SPEAKER_01"
  }
 ],
 [
  {
   "start": 318.90096875,
   "end": 319.59284375000004
  },
  {
   "CU": "SPEAKER_00"
  }
 ],
 [
  {
   "start": 322.02284375,
   "end": 322.20846875
  },
  {
   "CV": "SPEAKER_00"
  }
 ],
 [
  {
   "start": 323.01846875,
   "end": 341.20971875000004
  },
  {
   "CW": "SPEAKER_00"
  }
 ],
 [
  {
   "start": 328.35096875000005,
   "end": 328.41846875000005
  },
  {
   "CX": "SPEAKER_02"
  }
 ],
 [
  {
   "start": 337.12596875,
   "end": 337.54784375
  },
  {
   "CY": "SPEAKER_01"
  }
 ],
 [
  {
   "start": 341.20971875000004,
   "end": 341.56409375000004
  },
  {
   "CZ": "SPEAKER_01"
  }
 ],
 [
  {
   "start": 341.56409375000004,
   "end": 350.84534375000004
  },
  {
   "DA": "SPEAKER_00"
  }
 ],
 [
  {
   "start": 350.99721875,
   "end": 352.97159375
  },
  {
   "DB": "SPEAKER_02"
  }
 ],
 [
  {
   "start": 353.25846875,
   "end": 367.60221875
  },
  {
   "DC": "SPEAKER_02"
  }
 ],
 [
  {
   "start": 364.26096875,
   "end": 364.53096875
  },
  {
   "DD": "SPEAKER_00"
  }
 ],
 [
  {
   "start": 367.24784375,
   "end": 374.03159375
  },
  {
   "DE": "SPEAKER_00"
  }
 ],
 [
  {
   "start": 374.16659375,
   "end": 382.23284375000003
  },
  {
   "DF": "SPEAKER_00"
  }
 ],
 [
  {
   "start": 379.26284375,
   "end": 379.39784375000005
  },
  {
   "DG": "SPEAKER_02"
  }
 ],
 [
  {
   "start": 382.23284375000003,
   "end": 382.55346875000004
  },
  {
   "DH": "SPEAKER_02"
  }
 ],
 [
  {
   "start": 382.55346875000004,
   "end": 382.58721875000003
  },
  {
   "DI": "SPEAKER_00"
  }
 ],
 [
  {
   "start": 382.58721875000003,
   "end": 406.26284375
  },
  {
   "DJ": "SPEAKER_02"
  }
 ],
 [
  {
   "start": 385.62471875,
   "end": 386.16471875
  },
  {
   "DK": "SPEAKER_00"
  }
 ],
 [
  {
   "start": 406.36409375000005,
   "end": 409.78971875
  },
  {
   "DL": "SPEAKER_03"
  }
 ],
 [
  {
   "start": 408.57471875000005,
   "end": 408.62534375
  },
  {
   "DM": "SPEAKER_02"
  }
 ],
 [
  {
   "start": 410.41409375,
   "end": 424.87596875
  },
  {
   "DN": "SPEAKER_03"
  }
 ],
 [
  {
   "start": 424.97721875,
   "end": 435.49034375
  },
  {
   "DO": "SPEAKER_03"
  }
 ],
 [
  {
   "start": 435.52409375,
   "end": 441.44721875000005
  },
  {
   "DP": "SPEAKER_03"
  }
 ],
 [
  {
   "start": 441.44721875000005,
   "end": 442.71284375000005
  },
  {
   "DQ": "SPEAKER_02"
  }
 ],
 [
  {
   "start": 442.51034375,
   "end": 444.60284375000003
  },
  {
   "DR": "SPEAKER_03"
  }
 ],
 [
  {
   "start": 444.60284375000003,
   "end": 444.97409375
  },
  {
   "DS": "SPEAKER_02"
  }
 ],
 [
  {
   "start": 444.97409375,
   "end": 448.23096875000005
  },
  {
   "DT": "SPEAKER_03"
  }
 ],
 [
  {
   "start": 448.23096875000005,
   "end": 448.31534375
  },
  {
   "DU": "SPEAKER_02"
  }
 ],
 [
  {
   "start": 448.31534375,
   "end": 449.80034375
  },
  {
   "DV": "SPEAKER_03"
  }
 ],
 [
  {
   "start": 449.80034375,
   "end": 455.36909375000005
  },
  {
   "DW": "SPEAKER_02"
  }
 ],
 [
  {
   "start": 451.42034375000003,
   "end": 451.52159375
  },
  {
   "DX": "SPEAKER_03"
  }
 ],
 [
  {
   "start": 451.82534375,
   "end": 452.93909375000004
  },
  {
   "DY": "SPEAKER_03"
  }
 ],
 [
  {
   "start": 453.39471875000004,
   "end": 453.64784375000005
  },
  {
   "DZ": "SPEAKER_03"
  }
 ],
 [
  {
   "start": 455.95971875000004,
   "end": 457.68096875000003
  },
  {
   "EA": "SPEAKER_03"
  }
 ],
 [
  {
   "start": 458.05221875,
   "end": 469.07159375000003
  },
  {
   "EB": "SPEAKER_03"
  }
 ],
 [
  {
   "start": 469.07159375000003,
   "end": 471.45096875
  },
  {
   "EC": "SPEAKER_02"
  }
 ],
 [
  {
   "start": 470.72534375000004,
   "end": 471.41721875
  },
  {
   "ED": "SPEAKER_03"
  }
 ],
 [
  {
   "start": 471.45096875,
   "end": 471.83909375
  },
  {
   "EE": "SPEAKER_03"
  }
 ],
 [
  {
   "start": 471.83909375,
   "end": 478.30221875
  },
  {
   "EF": "SPEAKER_02"
  }
 ],
 [
  {
   "start": 472.85159375,
   "end": 474.84284375000004
  },
  {
   "EG": "SPEAKER_03"
  }
 ],
 [
  {
   "start": 477.07034375,
   "end": 477.45846875
  },
  {
   "EH": "SPEAKER_03"
  }
 ],
 [
  {
   "start": 478.03221875,
   "end": 486.26721875000004
  },
  {
   "EI": "SPEAKER_03"
  }
 ],
 [
  {
   "start": 486.58784375000005,
   "end": 487.41471875
  },
  {
   "EJ": "SPEAKER_03"
  }
 ],
 [
  {
   "start": 487.60034375000004,
   "end": 488.10659375000006
  },
  {
   "EK": "SPEAKER_02"
  }
 ],
 [
  {
   "start": 488.32596875,
   "end": 499.58159375
  },
  {
   "EL": "SPEAKER_02"
  }
 ],
 [
  {
   "start": 495.16034375000004,
   "end": 495.21096875
  },
  {
   "EM": "SPEAKER_00"
  }
 ],
 [
  {
   "start": 495.21096875,
   "end": 495.49784375
  },
  {
   "EN": "SPEAKER_03"
  }
 ],
 [
  {
   "start": 499.90221875000003,
   "end": 500.15534375000004
  },
  {
   "EO": "SPEAKER_02"
  }
 ],
 [
  {
   "start": 500.15534375000004,
   "end": 500.18909375000004
  },
  {
   "EP": "SPEAKER_03"
  }
 ],
 [
  {
   "start": 500.18909375000004,
   "end": 500.30721875
  },
  {
   "EQ": "SPEAKER_02"
  }
 ],
 [
  {
   "start": 500.30721875,
   "end": 500.32409375000003
  },
  {
   "ER": "SPEAKER_03"
  }
 ],
 [
  {
   "start": 500.32409375000003,
   "end": 500.39159375
  },
  {
   "ES": "SPEAKER_02"
  }
 ],
 [
  {
   "start": 500.39159375,
   "end": 508.72784375000003
  },
  {
   "ET": "SPEAKER_03"
  }
 ],
 [
  {
   "start": 508.72784375000003,
   "end": 510.78659375
  },
  {
   "EU": "SPEAKER_02"
  }
 ],
 [
  {
   "start": 511.22534375000004,
   "end": 520.87784375
  },
  {
   "EV": "SPEAKER_02"
  }
 ],
 [
  {
   "start": 513.55409375,
   "end": 513.70596875
  },
  {
   "EW": "SPEAKER_03"
  }
 ],
 [
  {
   "start": 513.70596875,
   "end": 513.7734687500001
  },
  {
   "EX": "SPEAKER_00"
  }
 ],
 [
  {
   "start": 513.7734687500001,
   "end": 513.85784375
  },
  {
   "EY": "SPEAKER_03"
  }
 ],
 [
  {
   "start": 518.93721875,
   "end": 519.5615937499999
  },
  {
   "EZ": "SPEAKER_03"
  }
 ],
 [
  {
   "start": 520.87784375,
   "end": 532.8928437500001
  },
  {
   "FA": "SPEAKER_03"
  }
 ],
 [
  {
   "start": 533.4497187500001,
   "end": 537.2803437499999
  },
  {
   "FB": "SPEAKER_03"
  }
 ],
 [
  {
   "start": 534.96846875,
   "end": 535.60971875
  },
  {
   "FC": "SPEAKER_00"
  }
 ],
 [
  {
   "start": 537.5672187499999,
   "end": 541.0434687500001
  },
  {
   "FD": "SPEAKER_03"
  }
 ],
 [
  {
   "start": 541.0434687500001,
   "end": 541.1615937500001
  },
  {
   "FE": "SPEAKER_02"
  }
 ],
 [
  {
   "start": 541.1615937500001,
   "end": 543.52409375
  },
  {
   "FF": "SPEAKER_03"
  }
 ],
 [
  {
   "start": 543.4397187500001,
   "end": 543.4734687499999
  },
  {
   "FG": "SPEAKER_02"
  }
 ],
 [
  {
   "start": 543.52409375,
   "end": 544.18221875
  },
  {
   "FH": "SPEAKER_02"
  }
 ],
 [
  {
   "start": 544.18221875,
   "end": 544.90784375
  },
  {
   "FI": "SPEAKER_03"
  }
 ],
 [
  {
   "start": 544.78971875,
   "end": 545.9709687500001
  },
  {
   "FJ": "SPEAKER_02"
  }
 ],
 [
  {
   "start": 544.9753437500001,
   "end": 545.02596875
  },
  {
   "FK": "SPEAKER_03"
  }
 ],
 [
  {
   "start": 545.05971875,
   "end": 545.07659375
  },
  {
   "FL": "SPEAKER_03"
  }
 ],
 [
  {
   "start": 545.9709687500001,
   "end": 546.15659375
  },
  {
   "FM": "SPEAKER_03"
  }
 ],
 [
  {
   "start": 546.15659375,
   "end": 546.57846875
  },
  {
   "FN": "SPEAKER_02"
  }
 ],
 [
  {
   "start": 546.57846875,
   "end": 567.28409375
  },
  {
   "FO": "SPEAKER_03"
  }
 ],
 [
  {
   "start": 546.61221875,
   "end": 547.16909375
  },
  {
   "FP": "SPEAKER_02"
  }
 ],
 [
  {
   "start": 562.39034375,
   "end": 563.04846875
  },
  {
   "FQ": "SPEAKER_02"
  }
 ],
 [
  {
   "start": 564.29721875,
   "end": 564.34784375
  },
  {
   "FR": "SPEAKER_02"
  }
 ],
 [
  {
   "start": 567.1828437500001,
   "end": 582.4209687499999
  },
  {
   "FS": "SPEAKER_02"
  }
 ],
 [
  {
   "start": 580.22721875,
   "end": 580.4297187500001
  },
  {
   "FT": "SPEAKER_00"
  }
 ],
 [
  {
   "start": 582.4209687499999,
   "end": 610.04534375
  },
  {
   "FU": "SPEAKER_00"
  }
 ],
 [
  {
   "start": 589.4240937500001,
   "end": 589.9640937500001
  },
  {
   "FV": "SPEAKER_02"
  }
 ],
 [
  {
   "start": 592.5290937500001,
   "end": 592.7822187500001
  },
  {
   "FW": "SPEAKER_01"
  }
 ],
 [
  {
   "start": 610.01159375,
   "end": 611.69909375
  },
  {
   "FX": "SPEAKER_01"
  }
 ],
 [
  {
   "start": 611.85096875,
   "end": 617.03159375
  },
  {
   "FY": "SPEAKER_01"
  }
 ],
 [
  {
   "start": 617.03159375,
   "end": 618.02721875
  },
  {
   "FZ": "SPEAKER_02"
  }
 ],
 [
  {
   "start": 618.02721875,
   "end": 627.5278437500001
  },
  {
   "GA": "SPEAKER_01"
  }
 ],
 [
  {
   "start": 618.1453437499999,
   "end": 619.57971875
  },
  {
   "GB": "SPEAKER_02"
  }
 ],
 [
  {
   "start": 620.1028437500001,
   "end": 620.8959687500001
  },
  {
   "GC": "SPEAKER_02"
  }
 ],
 [
  {
   "start": 621.9253437500001,
   "end": 622.9040937500001
  },
  {
   "GD": "SPEAKER_02"
  }
 ],
 [
  {
   "start": 627.6459687500001,
   "end": 628.2197187500001
  },
  {
   "GE": "SPEAKER_01"
  }
 ]
]